{"ticker": "FICO", "name": "Fair Isaac Corporation", "sector": "Information Technology", "subIndustry": "Software & Services - Data Analytics & Decision Management", "businessModelSummary": "Fair Isaac develops predictive analytics and decision management software platforms that enable organizations to assess credit risk, detect fraud, and manage customer relationships. The company generates revenue through software subscriptions, services, and the licensing of its proprietary FICO Score credit scoring model, which is widely adopted across financial services.", "endMarkets": ["Financial Services & Banking", "Insurance", "Consumer Finance & Credit", "Telecommunications", "Healthcare & Pharmaceuticals"], "competitors": ["Equifax", "Experian", "TransUnion", "SAS Institute", "IBM"], "suppliers": ["Amazon Web Services", "Microsoft Azure", "Data providers and exchanges", "Cloud infrastructure vendors", "Consulting and systems integration firms"], "customers": ["Major banks and financial institutions", "Credit card issuers", "Insurance companies", "Retailers and consumer finance companies"], "distributors": ["Direct sales force", "Cloud platforms (AWS, Microsoft Azure)", "Systems integrators and consulting partners", "Technology resellers"], "regulators": ["Federal Reserve", "Consumer Financial Protection Bureau (CFPB)", "SEC (Securities and Exchange Commission)", "Office of the Comptroller of the Currency (OCC)"], "industryBodies": ["Consumer Data Industry Association", "Financial Industry Regulatory Authority (FINRA)", "American Financial Services Association"]}