[{"name": "David Moreno", "currentRole": "Vice President, Engine Leasing", "formerRole": "N/A", "companyAffiliation": "FTAI Aviation", "ecosystemNode": "competitor", "expertise": ["Engine Leasing", "MRO Services", "Aviation Asset Management"], "yearsExperience": 15, "connectionToCompany": "FTAI Aviation competes directly with StandardAero in CFM56 and V2500 engine MRO and leasing markets", "score": {"proximity": 3, "recency": 3, "relevance": 4, "uniqueness": 3}, "linkedinUrl": "", "sourceNote": "Could not verify a specific individual with this name and title at FTAI Aviation \u2014 flagged for removal per accuracy rules", "id": 1}]